fluidtopics/markdown/__init__.py
fluidtopics/markdown/attachment.py
fluidtopics/markdown/cli.py
fluidtopics/markdown/errors.py
fluidtopics/markdown/ftmap.py
fluidtopics/markdown/ftsession.py
fluidtopics/markdown/metadata.py
fluidtopics_markdown-0.13.5.dist-info/entry_points.txt
fluidtopics_markdown-0.13.5.dist-info/METADATA
fluidtopics_markdown-0.13.5.dist-info/WHEEL
fluidtopics_markdown-0.13.5.dist-info/RECORD
